[
  {
    "code": "ut",
    "title": "utilities",
    "desc": null,
    "val": null,
    "unit": null,
    "icon": "",
    "favicon": "check-circle",
    "type": "productAttributes",
    "order": 12
  },
  {
    "code": "ot",
    "title": "other",
    "desc": null,
    "val": null,
    "unit": null,
    "icon": null,
    "favicon": "check-circle",
    "type": "productAttributes",
    "order": 13
  },
  {
    "code": "he",
    "title": "heating",
    "desc": null,
    "val": null,
    "unit": null,
    "icon": null,
    "favicon": "",
    "type": "productAttributes",
    "order": 14
  },
  {
    "code": "ec",
    "title": "energy class",
    "desc": null,
    "val": null,
    "unit": null,
    "icon": null,
    "favicon": null,
    "type": "productAttributes",
    "order": 15
  },
  {
    "code": "or",
    "title": "orientation",
    "desc": null,
    "val": null,
    "unit": null,
    "icon": null,
    "favicon": null,
    "type": "productAttributes",
    "order": 16
  },
  {
    "code": "tr",
    "title": "transport",
    "desc": null,
    "val": null,
    "unit": null,
    "icon": null,
    "favicon": null,
    "type": "productAttributes",
    "order": 17
  },
  {
    "code": "te",
    "title": "terrace area",
    "desc": null,
    "val": null,
    "unit": "m²",
    "icon": null,
    "favicon": null,
    "type": "productAttributes",
    "order": 18
  },
  {
    "code": "ct",
    "title": "close to",
    "desc": null,
    "val": null,
    "unit": null,
    "icon": null,
    "favicon": "check-circle",
    "type": "productCloseTo",
    "order": 19
  },
  {
    "code": "pr_eu",
    "title": "price",
    "desc": null,
    "val": null,
    "unit": "€",
    "icon": null,
    "favicon": null,
    "type": "productDetails",
    "order": 1
  },
  {
    "code": "pr_kn",
    "title": "price hrk",
    "desc": null,
    "val": null,
    "unit": "kn",
    "icon": null,
    "favicon": null,
    "type": "productDetails",
    "order": 2
  },
  {
    "code": "lo",
    "title": "location",
    "desc": null,
    "val": null,
    "unit": null,
    "icon": null,
    "favicon": null,
    "type": "productDetails",
    "order": 3
  },
  {
    "code": "tra",
    "title": "transaction",
    "desc": null,
    "val": null,
    "unit": null,
    "icon": null,
    "favicon": null,
    "type": "productDetails",
    "order": 4
  },
  {
    "code": "rt",
    "title": "realestate type",
    "desc": null,
    "val": null,
    "unit": null,
    "icon": null,
    "favicon": null,
    "type": "productDetails",
    "order": 5
  },
  {
    "code": "ss",
    "title": "square size",
    "desc": null,
    "val": null,
    "unit": "m²",
    "icon": null,
    "favicon": null,
    "type": "productDetails",
    "order": 6
  },
  {
    "code": "totr",
    "title": "total rooms",
    "desc": null,
    "val": null,
    "unit": null,
    "icon": null,
    "favicon": null,
    "type": "productDetails",
    "order": 7
  },
  {
    "code": "br",
    "title": "bedrooms",
    "desc": null,
    "val": null,
    "unit": null,
    "icon": null,
    "favicon": null,
    "type": "productDetails",
    "order": 8
  },
  {
    "code": "bar",
    "title": "bathrooms",
    "desc": null,
    "val": null,
    "unit": null,
    "icon": null,
    "favicon": null,
    "type": "productDetails",
    "order": 9
  },
  {
    "code": "fl",
    "title": "floor",
    "desc": null,
    "val": null,
    "unit": null,
    "icon": null,
    "favicon": null,
    "type": "productDetails",
    "order": 10
  },
  {
    "code": "totf",
    "title": "total floors",
    "desc": null,
    "val": null,
    "unit": null,
    "icon": null,
    "favicon": null,
    "type": "productDetails",
    "order": 11
  }

]